{
    "Year": {
        "Primer": {
            "Primer": [
                {"code":"CCOM3001", "name":"Programacion Basica I", "credits":4}
            ],
            "Segundo": [
            ]
        },

        "Segundo": {
            "Primer": [
                {"code":"Sentra", "name":4, "credits":3},
                {"code":"Sentra", "name":4, "credits":3},
                {"code":"Sentra", "name":4, "credits":3},
                {"code":"Sentra", "name":4, "credits":3}
            ],
            "Segundo": [
                {"code":"Sentra", "name":4, "credits":3},
                {"code":"Sentra", "name":4, "credits":3},
                {"code":"Sentra", "name":4, "credits":3},
                {"code":"Sentra", "name":4, "credits":3}
            ]
        },

        "Tercer": {
            "Primer": [
                {"code":"Sentra", "name":4, "credits":3},
                {"code":"Sentra", "name":4, "credits":3},
                {"code":"Sentra", "name":4, "credits":3},
                {"code":"Sentra", "name":4, "credits":3}
            ],
            "Segundo": [
                {"code":"Sentra", "name":4, "credits":3},
                {"code":"Sentra", "name":4, "credits":3},
                {"code":"Sentra", "name":4, "credits":3},
                {"code":"Sentra", "name":4, "credits":3}
            ]
        },

        "Cuarto": {
            "Primer": [
                {"code":"Sentra", "name":4, "credits":3},
                {"code":"Sentra", "name":4, "credits":3},
                {"code":"Sentra", "name":4, "credits":3},
                {"code":"Sentra", "name":4, "credits":3}
            ],
            "Segundo": [
                {"code":"Sentra", "name":4, "credits":3},
                {"code":"Sentra", "name":4, "credits":3},
                {"code":"Sentra", "name":4, "credits":3},
                {"code":"Sentra", "name":4, "credits":3}
            ]
        }
    }
    }
   
